{
  "eyebrow": "Prenota",
  "headlineHtml": "Duecentotrent'anni <em>di benvenuti.</em> Il prossimo lo abbiamo tenuto per voi.",
  "subtext": "Prenota direttamente per la migliore tariffa disponibile. Preventivi personalizzati su richiesta — i prezzi possono variare a seconda del giorno della settimana, della stagione e degli eventi.",
  "primaryCta": {
    "label": "Prenota ora",
    "href": "https://www.simplebooking.it/ibe2/hotel/11642?lang=EN&cur=CHF"
  },
  "phone": {
    "label": "+41 81 354 90 90",
    "href": "tel:+41813549090"
  }
}
