{
  "title": "Hotel Economico nel Centro Storico di Coira | Hotel Drei Könige · Dal 1793",
  "description": "Un hotel a conduzione familiare 3 stelle nel centro storico di Coira, la città più antica della Svizzera. Camere arredate individualmente da CHF 95/notte. Wi-Fi gratuito, colazione & deposito bici. A 7 min dalla stazione. Prenota direttamente per le migliori tariffe.",
  "ogImage": "/images/chur-switzerland-alpine-dusk-panorama.jpg",
  "ogImageAlt": "Veduta panoramica del centro storico di Coira, in Svizzera, durante l'ora blu al crepuscolo.",
  "favicon": "/favicon.svg"
}
